githubcutter/__init__.py
githubcutter/cli.py
githubcutter/commands.py
githubcutter/config.py
githubcutter/entity.py
githubcutter-0.3.1.dev0.dist-info/LICENSE
githubcutter-0.3.1.dev0.dist-info/METADATA
githubcutter-0.3.1.dev0.dist-info/WHEEL
githubcutter-0.3.1.dev0.dist-info/entry_points.txt
githubcutter-0.3.1.dev0.dist-info/top_level.txt
githubcutter-0.3.1.dev0.dist-info/RECORD
