Metadata-Version: 2.1
Name: githubcutter
Version: 0.3.1.dev0
Summary: A tool to setup GitHub repositories using simple YAML templates
Home-page: https://github.com/stracquadaniolab/githubcutter
Author: Giovanni Stracquadanio
Author-email: giovanni.stracquadanio@ed.ac.uk
License: MIT
Keywords: version-control git automation
Platform: UNKNOWN
Requires-Dist: argh (>=0.26)
Requires-Dist: python-dotenv (>=0.10)
Requires-Dist: PyYAML (>=5.1)
Requires-Dist: PyGithub (>=1.43)
Requires-Dist: dotty-dict (>=1.1)
